pysnake/__init__.py
pysnake/__main__.py
pysnake/arena.py
pysnake/exeptions.py
pysnake/game.py
pysnake/settings.py
pysnake/windows.py
pysnake-1.0.0.dist-info/DESCRIPTION.rst
pysnake-1.0.0.dist-info/METADATA
pysnake-1.0.0.dist-info/RECORD
pysnake-1.0.0.dist-info/WHEEL
pysnake-1.0.0.dist-info/entry_points.txt
pysnake-1.0.0.dist-info/metadata.json
pysnake-1.0.0.dist-info/top_level.txt
